{
	"animations": [
		{
			"offsets": [
				0,
				0
			],
			"loop": false,
			"fps": 24,
			"anim": "danceLeft",
			"indices": [],
			"name": "Sonic Idle Left"
		},
		{
			"offsets": [
				-10,
				0
			],
			"loop": false,
			"fps": 24,
			"anim": "danceRight",
			"indices": [],
			"name": "Sonic Idle Right"
		}
	],
	"no_antialiasing": true,
	"image": "characters/sprites-p2/gf_sprites",
	"position": [
		-370,
		450
	],
	"healthicon": "none",
	"flip_x": false,
	"healthbar_colors": [
		0,
		0,
		0
	],
	"camera_position": [
		0,
		-250
	],
	"sing_duration": 4,
	"scale": 10
}